README.md
setup.cfg
setup.py
clickutils/__init__.py
clickutils/types.py
clickutils/utils.py
clickutils/viewsets.py
clickutils.egg-info/PKG-INFO
clickutils.egg-info/SOURCES.txt
clickutils.egg-info/dependency_links.txt
clickutils.egg-info/requires.txt
clickutils.egg-info/top_level.txt