Metadata-Version: 2.1
Name: clickutils
Version: 0.1.5
Summary: Extra utils for click library
Home-page: https://www.github.com/tannerburns/clickutils
Author: Tanner Burns
Author-email: tjburns102@gmail.com
License: UNKNOWN
Platform: UNKNOWN
Classifier: Operating System :: OS Independent
Classifier: Programming Language :: Python :: 3.7
